catqdm/__init__.py
catqdm/big_cat_bar.py
catqdm/catbar.py
catqdm/faces.py
catqdm-0.1.1.dist-info/LICENSE
catqdm-0.1.1.dist-info/METADATA
catqdm-0.1.1.dist-info/WHEEL
catqdm-0.1.1.dist-info/RECORD
