Metadata-Version: 2.3
Name: catqdm
Version: 0.1.1
Summary: Simple tqdm bar with asci cat faces.
License: MIT
Author: Aloys Bernard
Author-email: aloys.bernard@artefact.com
Requires-Python: >=3.10
Classifier: License :: OSI Approved :: MIT License
Classifier: Programming Language :: Python :: 3
Classifier: Programming Language :: Python :: 3.10
Classifier: Programming Language :: Python :: 3.11
Classifier: Programming Language :: Python :: 3.12
Classifier: Programming Language :: Python :: 3.13
Requires-Dist: tqdm (>=4.67.1,<5.0.0)
